{"2023-02-07":{"time":{"updated":"Feb 1, 2023 00:17:00 UTC","updatedISO":"2023-02-01T00:17:00+00:00","updateduk":"Feb 1, 2023 at 00:17 GMT"},"disclaimer":"This data was produced from the CoinDesk Bitcoin Price Index (USD). Non-USD currency data converted using hourly conversion rate from openexchangerates.org","chartName":"Bitcoin","bpi":{"USD":{"code":"USD","symbol":"&#36;","rate":"23,078.0638","description":"United States Dollar","rate_float":23078.0638},"GBP":{"code":"GBP","symbol":"&pound;","rate":"19,283.8455","description":"British Pound Sterling","rate_float":19283.8455},"EUR":{"code":"EUR","symbol":"&euro;","rate":"22,481.4035","description":"Euro","rate_float":22481.4035},"CNY":{"code":"CNY","symbol":"&yen;","rate":"40,202.5000","description":"Chinese Yuan","rate_float":40202.5}}},"2024-12-30":{"time":{"updated":"Dec 1, 2024 00:01:23 UTC","updatedISO":"2024-12-01T00:01:23+00:00","updateduk":"Dec 1, 2024 at 00:01 GMT"},"disclaimer":"This data was produced from the CoinDesk Bitcoin Price Index (USD). Non-USD currency data converted using hourly conversion rate from openexchangerates.org","chartName":"Bitcoin","bpi":{"USD":{"code":"USD","symbol":"&#36;","rate":"96,379.979","description":"United States Dollar","rate_float":96379.9792},"GBP":{"code":"GBP","symbol":"&pound;","rate":"75,693.077","description":"British Pound Sterling","rate_float":75693.0769},"EUR":{"code":"EUR","symbol":"&euro;","rate":"91,113.584","description":"Euro","rate_float":91113.5844},"CNY":{"code":"CNY","symbol":"&yen;","rate":"697,954.896","description":"Chinese Yuan","rate_float":697954.8955}}}}