{"time":{"updated":"Mar 6, 2024 00:00:52 UTC","updatedISO":"2024-03-06T00:00:52+00:00","updateduk":"Mar 6, 2024 at 00:00 GMT"},"disclaimer":"This data was produced from the CoinDesk Bitcoin Price Index (USD). Non-USD currency data converted using hourly conversion rate from openexchangerates.org","chartName":"Bitcoin","bpi":{"USD":{"code":"USD","symbol":"&#36;","rate":"63,915.628","description":"United States Dollar","rate_float":63915.6281},"GBP":{"code":"GBP","symbol":"&pound;","rate":"50,303.9","description":"British Pound Sterling","rate_float":50303.9003},"EUR":{"code":"EUR","symbol":"&euro;","rate":"58,869.553","description":"Euro","rate_float":58869.5532},"CNY":{"code":"CNY","symbol":"&yen;","rate":"460,000.775","description":"Chinese Yuan","rate_float":460000.7754}}}